syft_accounting_sdk/__init__.py
syft_accounting_sdk/cli.py
syft_accounting_sdk/core.py
syft_accounting_sdk/error.py
syft_accounting_sdk/schemas.py
syft_accounting_sdk-0.1.1.dist-info/METADATA
syft_accounting_sdk-0.1.1.dist-info/WHEEL
syft_accounting_sdk-0.1.1.dist-info/entry_points.txt
syft_accounting_sdk-0.1.1.dist-info/RECORD
